PriceIndexCalc/__init__.py
PriceIndexCalc/pandas_modules/__init__.py
PriceIndexCalc/pandas_modules/bilateral.py
PriceIndexCalc/pandas_modules/chaining.py
PriceIndexCalc/pandas_modules/extension_methods.py
PriceIndexCalc/pandas_modules/helpers.py
PriceIndexCalc/pandas_modules/index_methods.py
PriceIndexCalc/pandas_modules/multilateral.py
PriceIndexCalc/pandas_modules/weighted_least_squares.py
PriceIndexCalc/pyspark_modules/__init__.py
PriceIndexCalc/pyspark_modules/chaining.py
PriceIndexCalc/pyspark_modules/helpers.py
PriceIndexCalc/pyspark_modules/index_methods.py
PriceIndexCalc/pyspark_modules/multilateral.py
PriceIndexCalc/pyspark_modules/native_spark_gk.py
PriceIndexCalc/pyspark_modules/weighted_least_squares.py
PriceIndexCalc-0.7.dist-info/LICENSE
PriceIndexCalc-0.7.dist-info/METADATA
PriceIndexCalc-0.7.dist-info/WHEEL
PriceIndexCalc-0.7.dist-info/top_level.txt
PriceIndexCalc-0.7.dist-info/RECORD
