Metadata-Version: 2.1
Name: PriceIndexCalc
Version: 0.7
Summary: Price Index Calculator using bilateral and multilateral methods
Home-page: https://github.com/drrobotk/PriceIndexCalc
Author: Dr. Usman Kayani
Author-email: usman.kayaniphd@gmail.com
License: MIT
Classifier: Programming Language :: Python :: 3
Classifier: License :: OSI Approved :: MIT License
Classifier: Operating System :: OS Independent
Requires-Python: >=3.7.1
License-File: LICENSE
Requires-Dist: pandas
Requires-Dist: numpy
Requires-Dist: scipy
